django_pgviews/__init__.py
django_pgviews/apps.py
django_pgviews/checks.py
django_pgviews/compat.py
django_pgviews/db/__init__.py
django_pgviews/db/fields.py
django_pgviews/db/migrations/__init__.py
django_pgviews/db/migrations/autodetector.py
django_pgviews/db/migrations/operations.py
django_pgviews/dependencies.py
django_pgviews/exceptions.py
django_pgviews/management/__init__.py
django_pgviews/management/commands/__init__.py
django_pgviews/management/commands/clear_pgviews.py
django_pgviews/management/commands/makemigrations.py
django_pgviews/management/commands/migrate.py
django_pgviews/management/commands/refresh_pgviews.py
django_pgviews/management/commands/sync_pgviews.py
django_pgviews/management/operations/__init__.py
django_pgviews/management/operations/_utils.py
django_pgviews/management/operations/clear.py
django_pgviews/management/operations/create.py
django_pgviews/management/operations/create_materialized.py
django_pgviews/managers.py
django_pgviews/models.py
django_pgviews/py.typed
django_pgviews/querysets.py
django_pgviews/refresh.py
django_pgviews/signals.py
django_pgviews/view.py
django_pgviews_redux-1.1.0.dist-info/METADATA
django_pgviews_redux-1.1.0.dist-info/WHEEL
django_pgviews_redux-1.1.0.dist-info/RECORD
