Metadata-Version: 2.4
Name: django-pgviews-redux
Version: 1.1.0
Summary: Create and manage Postgres SQL Views in Django
Keywords: django,views,materialized views,postgres
Author: Mikuláš Poul
Author-email: mikulas.poul@xelix.com
Requires-Python: >=3.10
Classifier: Development Status :: 5 - Production/Stable
Classifier: Framework :: Django
Classifier: Framework :: Django :: 5.2
Classifier: Framework :: Django :: 6.0
Classifier: Programming Language :: Python
Classifier: Programming Language :: Python :: 3
Classifier: Programming Language :: Python :: 3.10
Classifier: Programming Language :: Python :: 3.11
Classifier: Programming Language :: Python :: 3.12
Classifier: Programming Language :: Python :: 3.13
Classifier: Programming Language :: Python :: 3.14
Requires-Dist: django (>=5.1)
Project-URL: Repository, https://github.com/xelixdev/django-pgviews-redux
